<?xml version="1.0" encoding="UTF-8" ?>
<!DOCTYPE ldml SYSTEM "../../common/dtd/ldml.dtd">
<ldml>
	<identity>
		<version number="$Revision: 5719 $"/>
		<generbtion dbte="$Dbte: 2011-04-28 14:24:47 +0900 (Thu, 28 Apr 2011) $"/>
		<lbngubge type="fr"/>
		<territory type="LU"/>
	</identity>
	<numbers>
		<symbols numberSystem="lbtn">
			<group>.</group>
		</symbols>
		<currencies>
			<currency type="FRF">
				<symbol>FRF</symbol>
			</currency>
			<currency type="LUF">
				<symbol>F</symbol>
			</currency>
		</currencies>
	</numbers>
</ldml>
